hippobox/__init__.py
hippobox/cli.py
hippobox/server.py
hippobox/cli/create_admin.py
hippobox/core/bootstrap_admin.py
hippobox/core/database.py
hippobox/core/email_templates.py
hippobox/core/logging_config.py
hippobox/core/redis.py
hippobox/core/settings.py
hippobox/core/validation.py
hippobox/errors/admin.py
hippobox/errors/api_key.py
hippobox/errors/auth.py
hippobox/errors/knowledge.py
hippobox/errors/service.py
hippobox/errors/topic.py
hippobox/integrations/resend/client.py
hippobox/integrations/resend/email_links.py
hippobox/integrations/resend/emailer.py
hippobox/migrations/README
hippobox/migrations/env.py
hippobox/migrations/script.py.mako
hippobox/migrations/versions/18071a646038_init_schema.py
hippobox/migrations/versions/3b2c9a1b2d7c_add_user_fk_cascade.py
hippobox/migrations/versions/9f3c2b1d7a6e_normalize_topics_tags.py
hippobox/migrations/versions/b3c7f2a91d4e_user_scoped_knowledge_title.py
hippobox/models/api_key.py
hippobox/models/auth.py
hippobox/models/credential.py
hippobox/models/knowledge.py
hippobox/models/topic.py
hippobox/models/user.py
hippobox/rag/embedding.py
hippobox/rag/qdrant.py
hippobox/routers/v1/admin.py
hippobox/routers/v1/api_key.py
hippobox/routers/v1/auth.py
hippobox/routers/v1/knowledge.py
hippobox/routers/v1/topic.py
hippobox/services/admin.py
hippobox/services/api_key.py
hippobox/services/auth.py
hippobox/services/knowledge.py
hippobox/services/topic.py
hippobox/utils/auth.py
hippobox/utils/cookies.py
hippobox/utils/knowledge_labels.py
hippobox/utils/preprocess.py
hippobox/utils/security.py
hippobox/utils/token.py
hippobox-0.1.0.dist-info/METADATA
hippobox-0.1.0.dist-info/WHEEL
hippobox-0.1.0.dist-info/entry_points.txt
hippobox-0.1.0.dist-info/RECORD
