Metadata-Version: 2.4
Name: hippobox
Version: 0.1.0
Summary: HippoBox MCP + Knowledge Store Server
Requires-Python: >=3.13
Requires-Dist: aiosqlite>=0.19.0
Requires-Dist: alembic>=1.17.2
Requires-Dist: argon2-cffi>=25.1.0
Requires-Dist: asyncpg>=0.29.0
Requires-Dist: bcrypt>=5.0.0
Requires-Dist: black>=25.11.0
Requires-Dist: fakeredis>=2.23.0
Requires-Dist: fastapi-mcp>=0.4.0
Requires-Dist: fastapi>=0.110.0
Requires-Dist: flake8>=7.3.0
Requires-Dist: httpx>=0.27.0
Requires-Dist: isort>=7.0.0
Requires-Dist: langchain-openai>=1.0.3
Requires-Dist: mcp[cli]>=1.17.0
Requires-Dist: openai>=2.8.1
Requires-Dist: passlib>=1.7.4
Requires-Dist: pydantic>=2.6.0
Requires-Dist: pyjwt>=2.10.1
Requires-Dist: python-dotenv>=1.0.1
Requires-Dist: python-jose>=3.5.0
Requires-Dist: qdrant-client>=1.7.0
Requires-Dist: redis[hiredis]>=5.0
Requires-Dist: sqlalchemy>=2.0.0
Requires-Dist: uvicorn[standard]>=0.29.0
